Lupyta-0.0.3.dist-info/DESCRIPTION.rst
Lupyta-0.0.3.dist-info/METADATA
Lupyta-0.0.3.dist-info/RECORD
Lupyta-0.0.3.dist-info/WHEEL
Lupyta-0.0.3.dist-info/metadata.json
Lupyta-0.0.3.dist-info/top_level.txt
lupyta/__init__.py
lupyta/_compat.py
lupyta/app.py
