Metadata-Version: 2.0
Name: Lupyta
Version: 0.0.3
Summary: Lupyta instalador automático de PyQt4
Home-page: https://github.com/eortizromero/lupyta
Author: Edgardo Ortiz
Author-email: edgardoficial.yo@gmail.com
License: UNKNOWN
Platform: any
Requires-Dist: wget
